{
  "timestamp": "2026-02-01T16:37:03.776Z",
  "tests": [
    {
      "phase": 1,
      "duration": 10,
      "selectedProduct": {
        "title": "OnePlus 12 Pro",
        "price": 549,
        "seller": "FastPhone",
        "location": "Nice (06)",
        "daysAgo": 267,
        "condition": "Excellent état",
        "image": "https://fr.shopping.rakuten.com/pictures/0199e78c-e727-7461-b76e-6b9120a04642_L_NOPAD.jpg"
      },
      "motivations": [
        "condition",
        "marque"
      ],
      "otherReason": null
    },
    {
      "phase": 2,
      "duration": 30,
      "selectedProduct": {
        "title": "Xiaomi 14 Ultra",
        "price": 479,
        "seller": "ChinaTech",
        "location": "Nantes (44)",
        "daysAgo": 4,
        "condition": "Très bon état",
        "image": "https://fr.shopping.rakuten.com/photo/xiaomi-14-ultra-concu-avec-leica-76607534430_L.jpg"
      },
      "motivations": [
        "prix-bas",
        "condition",
        "marque"
      ],
      "otherReason": null
    },
    {
      "phase": 3,
      "duration": 60,
      "selectedProduct": {
        "title": "Google Pixel 9 Pro",
        "price": 649,
        "seller": "TechHub",
        "location": "Toulouse (31)",
        "daysAgo": 3,
        "condition": "Bon état",
        "image": "https://www.backmarket.fr/cdn-cgi/image/format%3Dauto%2Cquality%3D75%2Cwidth%3D1080/https://d2e6ccujb3mkqf.cloudfront.net/c4635131-355c-4f9c-8622-a53bbb4583b4-1_eca63382-43ef-4811-9a55-786dd314cd5a.jpg"
      },
      "motivations": [
        "prix-bas",
        "condition",
        "vendeur",
        "marque"
      ],
      "otherReason": null
    }
  ]
}